{
  "_id": "62354201",
  "reply_to": "",
  "reply_level": "1",
  "name": "Esmailzadeh",
  "url": "",
  "email": "e93538d86419a09aa53ad084b9afc29f",
  "date": "2010-07-15T12:03:29",
  "content": " بیش از نصف عمرمان را مشغول بافتن پرده ای از اوهام و فریب هستیم که آنچه هست را از چشمانمان دور بدارد و چه نا موفقیم در این تنها تلاشی که زندگیمان را اندکی انسانی و تا حدودی تاب آوردنی می کند. هر روز که خوب می نگریم گویی کار دیگری نداریم جز کنجکاوانه نگریستن این پرده که تنها فایده اش پنهان ساختن چیزیست که کنجکاوانه مجدد به دنبالش می گردیم گویی هرگز به عمد چنین پرده ای را ندوخته ایم و حال هم که کنجکاوانه می نگریم درمیابیم چه بسیارند سوراخ های ریز و درشتی که با دستان ظریف بافنده به عمد بر این پرده نقش بسته تا این بازی بی وقفه ادامه یابد. این سوراخ ها که خوب رسوامان کرد بجای برکندن و سیر دیدن آنچه هستیم سرمان را به زیر می اندازیم به این نشانه که چقدر شرم سار گشته ایم در باطن زیرکانه طرح پرده ای دیگر را در سر می پرورانیم اینگونه شلاق خورده نگاه غضب آلود خویش ایم و اغوا شده ی ظرافت دستان فریب گرمان\nhttp://localinside.persianblog.ir"
}